[
    {
        "id": "#2456JL",
        "product": "Nike Sportswear",
        "date": "Mar 12, 12:23 pm",
        "price": "₹ 134.00",
        "payment": "Transfer",
        "status": "Pending"
    },
    {
        "id": "#2789KM",
        "product": "Polo Shirt",
        "date": "Jul 12, 03:45 pm",
        "price": "₹ 1299.00",
        "payment": "Credit Card",
        "status": "Completed"
    },
    {
        "id": "#3012NP",
        "product": "Blouse",
        "date": "Nov 13, 09:12 am",
        "price": "₹ 899.00",
        "payment": "Debit Card",
        "status": "Processing"
    },
    {
        "id": "#3245QR",
        "product": "T-Shirt",
        "date": "Feb 13, 11:34 am",
        "price": "₹ 599.00",
        "payment": "UPI",
        "status": "Processing"
    },
    {
        "id": "#3478ST",
        "product": "Dress",
        "date": "Aug 13, 05:21 pm",
        "price": "₹ 1499.00",
        "payment": "Transfer",
        "status": "Completed"
    },
    {
        "id": "#3701UV",
        "product": "Watch",
        "date": "Apr 14, 10:05 am",
        "price": "₹ 5899.00",
        "payment": "Credit Card",
        "status": "Incomplete"
    },
    {
        "id": "#3934WX",
        "product": "Handbag",
        "date": "Dec 14, 02:17 pm",
        "price": "₹ 2499.00",
        "payment": "UPI",
        "status": "Processing"
    },
    {
        "id": "#4167YZ",
        "product": "Dress Shirt",
        "date": "May 14, 06:45 pm",
        "price": "₹ 1299.00",
        "payment": "Debit Card",
        "status": "Pending"
    },
    {
        "id": "#4390AB",
        "product": "Skirt",
        "date": "Sep 15, 08:33 am",
        "price": "₹ 899.00",
        "payment": "Transfer",
        "status": "Completed"
    },
    {
        "id": "#4623CD",
        "product": "Blazer",
        "date": "Jan 15, 01:12 pm",
        "price": "₹ 4999.00",
        "payment": "Credit Card",
        "status": "Processing"
    },
    {
        "id": "#4856EF",
        "product": "Watch",
        "date": "Oct 15, 05:37 pm",
        "price": "₹ 3299.00",
        "payment": "UPI",
        "status": "Completed"
    },
    {
        "id": "#5089GH",
        "product": "Sneakers",
        "date": "Jun 16, 09:20 am",
        "price": "₹ 2499.00",
        "payment": "Transfer",
        "status": "Incomplete"
    },
    {
        "id": "#5312IJ",
        "product": "Sandals",
        "date": "Mar 16, 11:55 am",
        "price": "₹ 999.00",
        "payment": "Debit Card",
        "status": "Processing"
    },
    {
        "id": "#5545KL",
        "product": "Belt",
        "date": "Jul 16, 04:40 pm",
        "price": "₹ 1599.00",
        "payment": "Credit Card",
        "status": "Completed"
    },
    {
        "id": "#5778MN",
        "product": "Earrings",
        "date": "Feb 17, 10:15 am",
        "price": "₹ 599.00",
        "payment": "UPI",
        "status": "Pending"
    },
    {
        "id": "#6001OP",
        "product": "Sunglasses",
        "date": "Nov 17, 02:30 pm",
        "price": "₹ 3999.00",
        "payment": "Transfer",
        "status": "Processing"
    },
    {
        "id": "#6234QR",
        "product": "Clutch",
        "date": "Aug 17, 06:10 pm",
        "price": "₹ 1299.00",
        "payment": "Credit Card",
        "status": "Completed"
    },
    {
        "id": "#6467ST",
        "product": "Dress Pants",
        "date": "Apr 18, 09:45 am",
        "price": "₹ 1799.00",
        "payment": "Debit Card",
        "status": "Processing"
    },
    {
        "id": "#6700UV",
        "product": "Bra",
        "date": "Dec 18, 01:20 pm",
        "price": "₹ 799.00",
        "payment": "UPI",
        "status": "Incomplete"
    },
    {
        "id": "#6933WX",
        "product": "Boxers",
        "date": "May 18, 04:55 pm",
        "price": "₹ 599.00",
        "payment": "Transfer",
        "status": "Completed"
    },
    {
        "id": "#7166YZ",
        "product": "Bra",
        "date": "Sep 19, 11:30 am",
        "price": "₹ 899.00",
        "payment": "Credit Card",
        "status": "Processing"
    },
    {
        "id": "#7399AB",
        "product": "Running Shoes",
        "date": "Jan 19, 03:15 pm",
        "price": "₹ 3499.00",
        "payment": "Debit Card",
        "status": "Pending"
    },
    {
        "id": "#7622CD",
        "product": "Sports Shoes",
        "date": "Oct 19, 06:40 pm",
        "price": "₹ 3299.00",
        "payment": "UPI",
        "status": "Completed"
    },
    {
        "id": "#7855EF",
        "product": "Suit",
        "date": "Jun 20, 10:05 am",
        "price": "₹ 8999.00",
        "payment": "Transfer",
        "status": "Processing"
    },
    {
        "id": "#8088GH",
        "product": "Kurta Set",
        "date": "Mar 20, 01:50 pm",
        "price": "₹ 1899.00",
        "payment": "Credit Card",
        "status": "Incomplete"
    },
    {
        "id": "#8321IJ",
        "product": "Jacket",
        "date": "Jul 20, 05:25 pm",
        "price": "₹ 2999.00",
        "payment": "Debit Card",
        "status": "Completed"
    },
    {
        "id": "#8554KL",
        "product": "Perfume",
        "date": "Feb 21, 09:10 am",
        "price": "₹ 4599.00",
        "payment": "UPI",
        "status": "Processing"
    },
    {
        "id": "#8787MN",
        "product": "Deodorant Set",
        "date": "Nov 21, 12:35 pm",
        "price": "₹ 399.00",
        "payment": "Transfer",
        "status": "Pending"
    },
    {
        "id": "#9020OP",
        "product": "Makeup Kit",
        "date": "Aug 21, 04:20 pm",
        "price": "₹ 1299.00",
        "payment": "Credit Card",
        "status": "Completed"
    },
    {
        "id": "#9253QR",
        "product": "Tie",
        "date": "Apr 22, 11:45 am",
        "price": "₹ 799.00",
        "payment": "Debit Card",
        "status": "Processing"
    },
    {
        "id": "#9486ST",
        "product": "Bracelet",
        "date": "Dec 22, 03:30 pm",
        "price": "₹ 2299.00",
        "payment": "UPI",
        "status": "Incomplete"
    },
    {
        "id": "#9719UV",
        "product": "Wallet",
        "date": "May 22, 07:15 pm",
        "price": "₹ 1999.00",
        "payment": "Transfer",
        "status": "Completed"
    },
    {
        "id": "#9952WX",
        "product": "Sling Bag",
        "date": "Sep 23, 10:40 am",
        "price": "₹ 1499.00",
        "payment": "Credit Card",
        "status": "Processing"
    },
    {
        "id": "#1025YZ",
        "product": "Backpack",
        "date": "Jan 23, 01:25 pm",
        "price": "₹ 1299.00",
        "payment": "Debit Card",
        "status": "Pending"
    },
    {
        "id": "#1058AB",
        "product": "Wallet",
        "date": "Oct 23, 05:50 pm",
        "price": "₹ 899.00",
        "payment": "UPI",
        "status": "Completed"
    },
    {
        "id": "#1091CD",
        "product": "Sweatshirt",
        "date": "Jun 24, 09:35 am",
        "price": "₹ 1799.00",
        "payment": "Transfer",
        "status": "Processing"
    },
    {
        "id": "#1124EF",
        "product": "Sweater",
        "date": "Mar 24, 12:20 pm",
        "price": "₹ 1599.00",
        "payment": "Credit Card",
        "status": "Incomplete"
    },
    {
        "id": "#1157GH",
        "product": "Hoodie",
        "date": "Jul 24, 04:05 pm",
        "price": "₹ 1999.00",
        "payment": "Debit Card",
        "status": "Completed"
    },
    {
        "id": "#1190IJ",
        "product": "Jumpsuit",
        "date": "Feb 25, 10:50 am",
        "price": "₹ 2299.00",
        "payment": "UPI",
        "status": "Processing"
    },
    {
        "id": "#1223KL",
        "product": "Sweater",
        "date": "Nov 25, 02:35 pm",
        "price": "₹ 1899.00",
        "payment": "Transfer",
        "status": "Pending"
    },
    {
        "id": "#1256MN",
        "product": "Jeans",
        "date": "Aug 25, 07:20 pm",
        "price": "₹ 1499.00",
        "payment": "Credit Card",
        "status": "Completed"
    },
    {
        "id": "#1289OP",
        "product": "Leggings",
        "date": "Apr 26, 09:45 am",
        "price": "₹ 699.00",
        "payment": "Debit Card",
        "status": "Processing"
    },
    {
        "id": "#1322QR",
        "product": "Casual Shirt",
        "date": "Dec 26, 01:30 pm",
        "price": "₹ 1099.00",
        "payment": "UPI",
        "status": "Incomplete"
    },
    {
        "id": "#1355ST",
        "product": "Mini Skirt",
        "date": "May 26, 05:15 pm",
        "price": "₹ 899.00",
        "payment": "Transfer",
        "status": "Completed"
    },
    {
        "id": "#1388UV",
        "product": "Chinos",
        "date": "Sep 27, 11:40 am",
        "price": "₹ 1599.00",
        "payment": "Credit Card",
        "status": "Processing"
    },
    {
        "id": "#1421WX",
        "product": "Maxi Skirt",
        "date": "Jan 27, 03:25 pm",
        "price": "₹ 1299.00",
        "payment": "Debit Card",
        "status": "Pending"
    },
    {
        "id": "#1454YZ",
        "product": "Bow Tie",
        "date": "Oct 27, 06:10 pm",
        "price": "₹ 499.00",
        "payment": "UPI",
        "status": "Completed"
    },
    {
        "id": "#1487AB",
        "product": "Tank Top",
        "date": "Jun 28, 10:35 am",
        "price": "₹ 599.00",
        "payment": "Transfer",
        "status": "Processing"
    },
    {
        "id": "#1520CD",
        "product": "Henley Shirt",
        "date": "Mar 28, 02:20 pm",
        "price": "₹ 899.00",
        "payment": "Credit Card",
        "status": "Incomplete"
    },
    {
        "id": "#1553EF",
        "product": "Necklace",
        "date": "Jul 28, 05:05 pm",
        "price": "₹ 1299.00",
        "payment": "Debit Card",
        "status": "Completed"
    },
    {
        "id": "#1586GH",
        "product": "Cargo Pants",
        "date": "Feb 29, 09:30 am",
        "price": "₹ 1799.00",
        "payment": "UPI",
        "status": "Processing"
    },
    {
        "id": "#1619IJ",
        "product": "Crop Top",
        "date": "Nov 29, 01:15 pm",
        "price": "₹ 699.00",
        "payment": "Transfer",
        "status": "Pending"
    },
    {
        "id": "#1652KL",
        "product": "Loafers",
        "date": "Aug 29, 04:50 pm",
        "price": "₹ 2499.00",
        "payment": "Credit Card",
        "status": "Completed"
    },
    {
        "id": "#1685MN",
        "product": "Palazzo Pants",
        "date": "Apr 30, 10:25 am",
        "price": "₹ 999.00",
        "payment": "Debit Card",
        "status": "Processing"
    },
    {
        "id": "#1718OP",
        "product": "Briefs",
        "date": "Dec 30, 02:10 pm",
        "price": "₹ 499.00",
        "payment": "UPI",
        "status": "Incomplete"
    },
    {
        "id": "#1751QR",
        "product": "Hair Accessories",
        "date": "May 30, 05:55 pm",
        "price": "₹ 399.00",
        "payment": "Transfer",
        "status": "Completed"
    },
    {
        "id": "#1784ST",
        "product": "Sweatpants",
        "date": "Sep 31, 11:20 am",
        "price": "₹ 1299.00",
        "payment": "Credit Card",
        "status": "Processing"
    },
    {
        "id": "#1817UV",
        "product": "Lingerie Set",
        "date": "Jan 31, 03:05 pm",
        "price": "₹ 1499.00",
        "payment": "Debit Card",
        "status": "Pending"
    },
    {
        "id": "#1850WX",
        "product": "Pocket Square",
        "date": "Oct 31, 06:50 pm",
        "price": "₹ 399.00",
        "payment": "UPI",
        "status": "Completed"
    }
]